setup.py
beautifulpredicates/__init__.py
beautifulpredicates/models.py
beautifulpredicates/predicates.py
beautifulpredicates/views.py
beautifulpredicates/tests/__init__.py
beautifulpredicates/tests/predicates.py
beautifulpredicates/tests/views.py
django_beautifulpredicates.egg-info/PKG-INFO
django_beautifulpredicates.egg-info/SOURCES.txt
django_beautifulpredicates.egg-info/dependency_links.txt
django_beautifulpredicates.egg-info/requires.txt
django_beautifulpredicates.egg-info/top_level.txt