Metadata-Version: 1.0
Name: django-beautifulpredicates
Version: 0.0.1
Summary: Library to provide a predicate dispatch for Django's generic views.
Home-page: https://github.com/hirokiky/django-beautifulpredicates/
Author: Hiroki KIYOHARA
Author-email: hirokiky@gmail.com
License: MIT License
Platform: UNKNOWN
Classifier: Development Status :: 1 - Planning
Classifier: Environment :: Plugins
Classifier: Framework :: Django
Classifier: Intended Audience :: Developers
Classifier: License :: OSI Approved :: MIT License
Classifier: Programming Language :: Python
Classifier: Topic :: Software Development :: Libraries :: Python Modules
